symmathSBML/__init__.py
symmathSBML/_version.py
symmathSBML/constants.py
symmathSBML/exceptions.py
symmathSBML/function_definition.py
symmathSBML/helpers.py
symmathSBML/kinetic_law.py
symmathSBML/make_roadrunner.py
symmathSBML/msgs.py
symmathSBML/persister.py
symmathSBML/reaction.py
symmathSBML/symmath_base.py
symmathSBML/symmath_sbml.py
symmathSBML/symmath_util.py
symmathSBML/sympy_util.py
symmathSBML/util.py
symmathSBML-0.1.0.dist-info/LICENSE
symmathSBML-0.1.0.dist-info/METADATA
symmathSBML-0.1.0.dist-info/WHEEL
symmathSBML-0.1.0.dist-info/top_level.txt
symmathSBML-0.1.0.dist-info/RECORD
