Metadata-Version: 2.1
Name: symmathSBML
Version: 0.1.0
Summary: Symbolic mathematics for SBML Models.
Home-page: https://github.com/ModelEngineering/symmathSBML
Author: Joseph L. Hellerstein, Jin Liu
Author-email: jlheller@uw.edu
License: UNKNOWN
Project-URL: Bug Tracker, https://github.com/ModelEngineering/symmathSBML/issues
Platform: UNKNOWN
Classifier: Development Status :: 3 - Alpha
Classifier: Intended Audience :: Developers
Classifier: Topic :: Scientific/Engineering :: Bio-Informatics
Classifier: License :: OSI Approved :: MIT License
Classifier: Programming Language :: Python :: 3.4
Classifier: Programming Language :: Python :: 3.5
Classifier: Programming Language :: Python :: 3.6
Classifier: Programming Language :: Python :: 3.7
Classifier: Programming Language :: Python :: 3.8
Requires: tellurium
Requires: jupyterlab
Requires: matplotlib
Requires: nose
Requires: numpy
Requires: pandas
Requires: pip
Requires: pythonlibsbml
Requires: seaborn
Requires: sympy
Requires-Python: >=3.7
License-File: LICENSE
